coospace_automation/__init__.py
coospace_automation/auth.py
coospace_automation/calendar.py
coospace_automation/coospace.py
coospace_automation/notification.py
coospace_automation-1.0.1.dist-info/METADATA
coospace_automation-1.0.1.dist-info/WHEEL
coospace_automation-1.0.1.dist-info/top_level.txt
coospace_automation-1.0.1.dist-info/RECORD
