Metadata-Version: 2.1
Name: coospace_automation
Version: 1.0.1
Summary: A simple automation tool that uses python and selenium to automate common actions on the SZTE Coospace website
Author-email: TacticalCamel <takacsbalazsg@gmail.com>
Project-URL: Homepage, https://github.com/TacticalCamel/coospace-automation
Project-URL: Issues, https://github.com/TacticalCamel/coospace-automation/issues
Requires-Python: >=3.8
Requires-Dist: selenium >=4.20.0
Requires-Dist: pwinput >=1.0.3
